argiope/__init__.py
argiope/materials.py
argiope/mesh.py
argiope/models.py
argiope/utils.py
argiope/abq/__init__.py
argiope/abq/abqpostproc.py
argiope/abq/pypostproc.py
argiope/templates/materials/Elastic.inp
argiope/templates/materials/ElasticPlastic.inp
argiope/templates/materials/Material.inp
argiope/templates/mesh/inp.inp
argiope/templates/mesh/inp.inp~
argiope/templates/mesh/xdmf.xdmf
argiope/templates/mesh/xdmf.xdmf~
argiope/templates/mesh/xdmf_attribute.xdmf
argiope-0.3.dist-info/DESCRIPTION.rst
argiope-0.3.dist-info/METADATA
argiope-0.3.dist-info/RECORD
argiope-0.3.dist-info/WHEEL
argiope-0.3.dist-info/metadata.json
argiope-0.3.dist-info/top_level.txt
