Metadata-Version: 2.0
Name: argiope
Version: 0.3
Summary: A framework for simpler finite element processing
Home-page: https://github.com/lcharleux/argiope
Author: Ludovic Charleux, Emile Roux
Author-email: ludovic.charleux@univ-smb.fr
License: GPL v3
Platform: UNKNOWN
Requires-Dist: jupyter
Requires-Dist: matplotlib
Requires-Dist: nbconvert
Requires-Dist: numpy
Requires-Dist: pandas
Requires-Dist: scipy
